face_access_detection/__init__.py
face_access_detection/detector.py
face_access_detection/models/best.pt
face_access_detection-0.1.1.dist-info/LICENSE
face_access_detection-0.1.1.dist-info/METADATA
face_access_detection-0.1.1.dist-info/WHEEL
face_access_detection-0.1.1.dist-info/top_level.txt
face_access_detection-0.1.1.dist-info/RECORD
