Metadata-Version: 2.1
Name: face-access-detection
Version: 0.1.1
Summary: A library for face access detection using YOLOv8
Home-page: https://github.com/Sehastrajit/face-access-detection
Author: Sehastrajit
Author-email: your.email@example.com
License: MIT
Platform: UNKNOWN
License-File: LICENSE
Requires-Dist: torch
Requires-Dist: opencv-python
Requires-Dist: ultralytics
Requires-Dist: numpy
